rpi_monitor/__init__.py
rpi_monitor/core.py
rpi_monitor/tests.py
rpi_monitor/workers.py
wf_rpi_monitor-0.0.1.dist-info/LICENSE
wf_rpi_monitor-0.0.1.dist-info/METADATA
wf_rpi_monitor-0.0.1.dist-info/WHEEL
wf_rpi_monitor-0.0.1.dist-info/entry_points.txt
wf_rpi_monitor-0.0.1.dist-info/top_level.txt
wf_rpi_monitor-0.0.1.dist-info/RECORD
