Metadata-Version: 2.1
Name: wf-rpi-monitor
Version: 0.0.1
Summary: Tools to monitor and log status of a Raspberry Pi
Home-page: https://github.com/WildflowerSchools/wf-rpi-monitor
Author: Theodore Quinn
Author-email: ted.quinn@wildflowerschools.org
License: UNKNOWN
Keywords: rpi
Platform: UNKNOWN
Classifier: Intended Audience :: Developers
Classifier: License :: OSI Approved :: MIT License
Classifier: Operating System :: POSIX :: IRIX
Classifier: Programming Language :: Python
Requires-Dist: click (>=7.1.2)
Requires-Dist: psutil (>=5.7.2)
